Metadata-Version: 2.1
Name: starwatchapi
Version: 0.1
Summary: STAR Watch API wrapper
Home-page: https://github.com/ivanfor/starwatchapi
Author: Iván Forcada
Author-email: ivan@forcada.info
License: Apache 2.0
Platform: UNKNOWN
License-File: LICENSE.txt
